<data><marketplaceId>A1PA6795UKMFR9</marketplaceId><quantity>1</quantity><orderId>305-1638145-6189123</orderId><merchantId>AHKKWU9KYB9JL</merchantId><customizationData><children><children><children><displayValue>null</displayValue><name>Dropdown-Option 1</name><label>Sportmotive</label><type>OptionCustomization</type><optionSelection/></children><children><displayValue>null</displayValue><name>Dropdown-Option 2</name><label>Tiere</label><type>OptionCustomization</type><optionSelection/></children><children><displayValue>null</displayValue><name>Dropdown-Option 3</name><label>Fahrzeuge, Berufe, Symbole</label><type>OptionCustomization</type><optionSelection/></children><children><children><image><imageName>7016ed12-70fd-447d-8365-fd5ce3750f12.jpg</imageName><buyerFilename>1000048823.jpg</buyerFilename></image><name/><label>Eigenes Bild / Eigenes Motiv</label><type>ImageCustomization</type></children><name>Bild 1</name><label>Bild 1</label><position><x>208</x><y>139</y></position><type>PlacementContainerCustomization</type><dimension><width>192</width><height>181</height></dimension><buyerPlacement><scale><scaleX>0.1820412760992879</scaleX><scaleY>0.1820412760992879</scaleY></scale><position><x>-2.466488313151217</x><y>-40.649253731343265</y></position><dimension><width>3367</width><height>2968</height></dimension><angleOfRotation>0</angleOfRotation></buyerPlacement></children><children><children><name/><label>Textgestaltung</label><type>FontCustomization</type><fontSelection><family>Alegreya</family></fontSelection></children><children><colorSelection><name>Silber</name><colorModel>rgb</colorModel><value>#b6b6b6</value></colorSelection><name/><label>Farbe Edelstahl</label><type>ColorCustomization</type></children><children><children><children><children><name/><inputValue>Sidney </inputValue><label>Textgestaltung unter dem Motiv</label><type>TextCustomization</type></children><priceDelta><amount>0</amount></priceDelta><type>FlatRatePriceDeltaContainerCustomization</type></children><name>Texteingabe 1</name><label>Texteingabe 1</label><position><x>206</x><y>263</y></position><type>PlacementContainerCustomization</type><dimension><width>193</width><height>137</height></dimension><buyerPlacement><scale><scaleX>0.5329606720092612</scaleX><scaleY>0.5329606720092612</scaleY></scale><position><x>250.97329577361842</x><y>310.0402608776041</y></position><dimension><width>191.36024938622944</width><height>72.58726141078837</height></dimension><angleOfRotation>0</angleOfRotation></buyerPlacement></children><children><children><children><name/><inputValue/><label>Textgestaltung über dem Motiv</label><type>TextCustomization</type></children><type>FlatRatePriceDeltaContainerCustomization</type></children><name>Texteingabe 2</name><label>Texteingabe 2</label><position><x>210</x><y>65</y></position><type>PlacementContainerCustomization</type><dimension><width>190</width><height>156</height></dimension></children><type>ContainerCustomization</type></children><name>Text 1</name><label>Text 1</label><type>ContainerCustomization</type></children><children><children><name/><inputValue/><label>Weitere Angaben zu Ihrer Bestellung</label><type>TextCustomization</type></children><name>Daten 1</name><label>Daten 1</label><type>FlatRatePriceDeltaContainerCustomization</type></children><type>FlatContainerCustomization</type></children><svg>343c77d1-d81e-3b09-ee9c-e3a58c6c60ba.svg</svg><name>Oberfläche 2</name><baseImage><imageUrl>https://m.media-amazon.com/images/S/gestalt-seller-images-prod-eu-west-1/A1PA6795UKMFR9/AHKKWU9KYB9JL/682c83e2-5db8-413e-a816-1c2bbb444004.png</imageUrl><dimension><width>2000</width><height>2000</height></dimension></baseImage><label>Gestalten Sie Ihre Flasche jetzt!</label><type>PreviewContainerCustomization</type><snapshot><imageName>d62f4455-cdcb-bb52-f2a1-ce40bd0f6663.jpg</imageName><dimension><width>400</width><height>400</height></dimension></snapshot></children><children><children><children><children><name/><label>Schriftart auswählen</label><type>FontCustomization</type><fontSelection><family>Lato</family></fontSelection></children><children><colorSelection><name>Edelstahl</name><colorModel>rgb</colorModel><value>#bab7b7</value></colorSelection><name/><label>Wir gravieren auf diese Flasche in Edelstahl</label><type>ColorCustomization</type></children><children><children><children><children><name/><inputValue/><label>Textelement 1 erstellen</label><type>TextCustomization</type></children><type>FlatRatePriceDeltaContainerCustomization</type></children><name>Texteingabe 1</name><label>Texteingabe 1</label><position><x>207</x><y>114</y></position><type>PlacementContainerCustomization</type><dimension><width>191</width><height>253</height></dimension></children><children><children><children><name/><inputValue/><label>Textelement 2 erstellen</label><type>TextCustomization</type></children><type>FlatRatePriceDeltaContainerCustomization</type></children><name>Texteingabe 2</name><label>Texteingabe 2</label><position><x>210</x><y>118</y></position><type>PlacementContainerCustomization</type><dimension><width>189</width><height>248</height></dimension></children><children><children><children><name/><inputValue/><label>Textelement 3 gestalten</label><type>TextCustomization</type></children><type>FlatRatePriceDeltaContainerCustomization</type></children><name>Texteingabe 3</name><label>Texteingabe 3</label><position><x>209</x><y>118</y></position><type>PlacementContainerCustomization</type><dimension><width>189</width><height>247</height></dimension></children><type>ContainerCustomization</type></children><name>Text 1</name><label>Text 1</label><type>ContainerCustomization</type></children><type>FlatContainerCustomization</type></children><svg>8348b91c-cbed-a598-aeb4-7a196ee26a26.svg</svg><name>Oberfläche 2</name><baseImage><imageUrl>https://m.media-amazon.com/images/S/gestalt-seller-images-prod-eu-west-1/A1PA6795UKMFR9/AHKKWU9KYB9JL/5ce6fd43-cc1b-46bc-b643-e0b5f7c34548.png</imageUrl><dimension><width>2000</width><height>2000</height></dimension></baseImage><label>Alternative: Sie wollen nur einen bestimmten Text auf der Flasche haben (ohne Bild)</label><type>PreviewContainerCustomization</type><snapshot><imageName>a5091d33-3d52-3af3-f1b2-2d7839cc726d.jpg</imageName><dimension><width>400</width><height>400</height></dimension></snapshot></children><type>PageContainerCustomization</type></customizationData><orderItemId>38032593947682</orderItemId><asin>B0D1R1F6WC</asin><customizationInfo><version3.0><surfaces><name>Gestalten Sie Ihre Flasche jetzt!</name><areas><optionValue/><name>Dropdown-Option 1</name><label>Sportmotive</label><customizationType>Options</customizationType></areas><areas><optionValue/><name>Dropdown-Option 2</name><label>Tiere</label><customizationType>Options</customizationType></areas><areas><optionValue/><name>Dropdown-Option 3</name><label>Fahrzeuge, Berufe, Symbole</label><customizationType>Options</customizationType></areas><areas><Position><x>208</x><y>139</y></Position><svgImage>343c77d1-d81e-3b09-ee9c-e3a58c6c60ba.svg</svgImage><name>Bild 1</name><Dimensions><width>192</width><height>181</height></Dimensions><customizationType>ImagePrinting</customizationType></areas><areas><Position><x>206</x><y>263</y></Position><svgImage>343c77d1-d81e-3b09-ee9c-e3a58c6c60ba.svg</svgImage><name>Texteingabe 1</name><Dimensions><width>193</width><height>137</height></Dimensions><priceDelta><value>0.0</value></priceDelta><customizationType>ImagePrinting</customizationType></areas><areas><colorName>Silber</colorName><fontFamily>Alegreya</fontFamily><Position><x>210</x><y>65</y></Position><name>Texteingabe 2</name><Dimensions><width>190</width><height>156</height></Dimensions><label>Textgestaltung über dem Motiv</label><text/><fill>#b6b6b6</fill><customizationType>TextPrinting</customizationType></areas><areas><name>Daten 1</name><label>Weitere Angaben zu Ihrer Bestellung</label><text/><customizationType>TextPrinting</customizationType></areas></surfaces><surfaces><name>Alternative: Sie wollen nur einen bestimmten Text auf der Flasche haben (ohne Bild)</name><areas><colorName>Edelstahl</colorName><fontFamily>Lato</fontFamily><Position><x>207</x><y>114</y></Position><name>Texteingabe 1</name><Dimensions><width>191</width><height>253</height></Dimensions><label>Textelement 1 erstellen</label><text/><fill>#bab7b7</fill><customizationType>TextPrinting</customizationType></areas><areas><colorName>Edelstahl</colorName><fontFamily>Lato</fontFamily><Position><x>210</x><y>118</y></Position><name>Texteingabe 2</name><Dimensions><width>189</width><height>248</height></Dimensions><label>Textelement 2 erstellen</label><text/><fill>#bab7b7</fill><customizationType>TextPrinting</customizationType></areas><areas><colorName>Edelstahl</colorName><fontFamily>Lato</fontFamily><Position><x>209</x><y>118</y></Position><name>Texteingabe 3</name><Dimensions><width>189</width><height>247</height></Dimensions><label>Textelement 3 gestalten</label><text/><fill>#bab7b7</fill><customizationType>TextPrinting</customizationType></areas></surfaces></version3.0></customizationInfo><title>LicusDesign Thermosflasche mit Gravur 750 ml Trinkflasche Personalisiert Personalisierte Trinkflasche mit Namen Trinkflasche Gravur Thermoskanne Gravur Thermosflasche Gravur Personalisierte Flasche</title><vendorCode><present>false</present></vendorCode></data>